waitress_raw/__init__.py
waitress_raw/__main__.py
waitress_raw/__version__.py
waitress_raw-1.0.0.dist-info/LICENSE
waitress_raw-1.0.0.dist-info/METADATA
waitress_raw-1.0.0.dist-info/WHEEL
waitress_raw-1.0.0.dist-info/entry_points.txt
waitress_raw-1.0.0.dist-info/top_level.txt
waitress_raw-1.0.0.dist-info/RECORD
